README.md
setup.cfg
setup.py
distributions_CJ/Binomialdistribution.py
distributions_CJ/Gaussiandistribution.py
distributions_CJ/Generaldistribution.py
distributions_CJ/__init__.py
distributions_CJ.egg-info/PKG-INFO
distributions_CJ.egg-info/SOURCES.txt
distributions_CJ.egg-info/dependency_links.txt
distributions_CJ.egg-info/not-zip-safe
distributions_CJ.egg-info/top_level.txt